flask_admin_s3_upload.py
flask_admin_s3_upload-0.1.4.dist-info/DESCRIPTION.rst
flask_admin_s3_upload-0.1.4.dist-info/METADATA
flask_admin_s3_upload-0.1.4.dist-info/RECORD
flask_admin_s3_upload-0.1.4.dist-info/WHEEL
flask_admin_s3_upload-0.1.4.dist-info/metadata.json
flask_admin_s3_upload-0.1.4.dist-info/top_level.txt
