Metadata-Version: 2.0
Name: flask-admin-s3-upload
Version: 0.1.4
Summary: Field types for allowing file and image uploads to Amazon S3 (as well as default local storage) in Flask-Admin.
Home-page: https://github.com/Jaza/flask-admin-s3-upload
Author: Jeremy Epstein
Author-email: jazepstein@gmail.com
License: UNKNOWN
Platform: any
Classifier: Development Status :: 2 - Pre-Alpha
Classifier: Environment :: Web Environment
Classifier: Intended Audience :: Developers
Classifier: Operating System :: OS Independent
Classifier: Programming Language :: Python
Classifier: Programming Language :: Python :: 2
Classifier: Programming Language :: Python :: 2.7
Classifier: Programming Language :: Python :: 3
Classifier: Programming Language :: Python :: 3.3
Requires-Dist: Flask-Admin
Requires-Dist: boto
Requires-Dist: url-for-s3
